{
  "stats": {
    "base_atk": 10000,
    "max_ammo": 120,
    "reload_time": 1.67,
    "damage_rate": 0.0447,
    "windup_frames": 12,
    "winddown_frames": 10,
    "core_hit_rate": 0.0
  },
  "name": "クエンシー",
  "weapon_type": "SMG",
  "element": "Electric",
  "class": "Supporter",
  "manufacturer": "ミシリス",
  "squad": "不明",
  "burst_skill": {
    "name": "Burst: 偉大なる脱出",
    "trigger_type": "on_start",
    "trigger_value": 0,
    "effect_type": "cumulative_stages",
    "kwargs": {
      "trigger_all_stages": true
    },
    "stages": [
      {
        "effect_type": "buff",
        "target": "self",
        "kwargs": {
          "buff_type": "max_hp_rate",
          "value": 0.4387,
          "duration": 5.0
        }
      },
      {
        "effect_type": "buff",
        "target": "self",
        "kwargs": {
          "buff_type": "crit_dmg_buff",
          "value": 0.299,
          "duration": 10
        }
      }
    ],
    "cooldown": 20.0
  },
  "skills": [
    {
      "name": "S1: 新しいルート",
      "trigger_type": "shot_count",
      "trigger_value": 1,
      "effect_type": "buff",
      "target": "self",
      "kwargs": {
        "buff_type": "max_hp_rate",
        "value": 0.1242,
        "duration": 10.0
      }
    },
    {
      "name": "S2: 隠れた共犯者",
      "trigger_type": "on_start",
      "trigger_value": 0,
      "effect_type": "buff",
      "target": "self",
      "kwargs": {
        "buff_type": "atk_buff_rate",
        "value": 0.1611,
        "duration": 5.0
      }
    }
  ]
}