{
  "stats": {
    "base_atk": 10000,
    "max_ammo": 300,
    "reload_time": 1.67,
    "damage_rate": 0.051,
    "windup_frames": 12,
    "winddown_frames": 10,
    "core_hit_rate": 0.0
  },
  "name": "ロザンナ",
  "weapon_type": "MG",
  "element": "Electric",
  "class": "Attacker",
  "manufacturer": "テトラ",
  "squad": "アンダーワールドクイーン",
  "burst_skill": {
    "name": "Burst: ヴェンデッタ",
    "trigger_type": "on_start",
    "trigger_value": 0,
    "effect_type": "damage",
    "target": "self",
    "kwargs": {
      "multiplier": 5.6160000000000005,
      "profile": {
        "is_skill_damage": true
      }
    },
    "cooldown": 40.0
  },
  "skills": [
    {
      "name": "S1: オン・ザ・ラム",
      "trigger_type": "shot_count",
      "trigger_value": 120,
      "effect_type": "buff",
      "target": "self",
      "kwargs": {
        "buff_type": "crit_rate_buff",
        "value": 0.1934,
        "duration": 10
      }
    },
    {
      "name": "S2: カポ・ディ・カピ",
      "trigger_type": "on_start",
      "trigger_value": 0,
      "effect_type": "stack_buff",
      "target": "self",
      "kwargs": {
        "buff_type": "atk_buff_rate",
        "value": 0.2261,
        "duration": 30.0,
        "max_stack": 5,
        "stack_name": "Stack_atk_buff_rate"
      }
    }
  ]
}