{
  "name": "ロザンナ：シックオーシャン",
  "weapon_type": "AR",
  "burst_stage": "2",
  "element": "Wind",
  "class": "Supporter",
  "squad": "アンダーワールドクイーン",
  "stats": {
    "max_ammo": 60,
    "reload_time": 1.00,
    "damage_rate": 0.1365,
    "core_damage_rate": 2.00
  },
  "skills": [
    {
      "name": "Skill 1: フェリータ (開幕)",
      "trigger_type": "on_start",
      "trigger_value": 0,
      "effect_type": "buff",
      "target": "allies",
      "kwargs": {
        "effect_no": 1,
        "buff_type": "part_dmg_buff",
        "value_list": [0.1433, 0.1544, 0.1654, 0.1764, 0.1874, 0.1985, 0.2095, 0.2205, 0.2316, 0.2426],
        "duration": 15
      }
    },
    {
      "name": "Skill 1: フェリータ (パーツ破壊時)",
      "trigger_type": "time_interval",
      "trigger_value": 15.0,
      "condition": {
        "simulation_flag": "special_mode"
      },
      "effect_type": "stack_buff",
      "target": "allies",
      "kwargs": {
        "effect_no": 2,
        "buff_type": "atk_buff_fixed",
        "scale_by_caster_stats": true,
        "target_stat": "atk",
        "max_stack": 5,
        "value_list": [0.0177, 0.0191, 0.0204, 0.0218, 0.0232, 0.0245, 0.0259, 0.0273, 0.0286, 0.03],
        "duration": 30,
        "description": "パーツ破壊時(special_mode/15秒毎): 発動者攻撃力基準で攻撃力UP (スタック)"
      }
    },
    {
      "name": "Skill 2: スピーナ・ディ・ローザ",
      "trigger_type": "time_interval",
      "trigger_value": 30.0,
      "effect_type": "cumulative_stages",
      "kwargs": {
        "trigger_all_stages": true
      },
      "stages": [
        {
          "effect_type": "buff",
          "target": "allies",
          "kwargs": {
            "effect_no": 3,
            "buff_type": "part_dmg_buff",
            "value_list": [0.1433, 0.1544, 0.1654, 0.1764, 0.1874, 0.1985, 0.2095, 0.2205, 0.2316, 0.2426],
            "duration": 15
          }
        },
        {
          "effect_type": "dot",
          "target": "enemy",
          "kwargs": {
            "effect_no": 4,
            "interval": 1.0,
            "multiplier_list": [0.416, 0.448, 0.48, 0.512, 0.544, 0.576, 0.608, 0.64, 0.672, 0.704],
            "duration": 15
          }
        }
      ]
    },
    {
      "name": "バースト: オンダ・グランデ",
      "trigger_type": "on_use_burst_skill",
      "trigger_value": 0,
      "effect_type": "cumulative_stages",
      "cooldown_time": 20.0,
      "kwargs": {
        "trigger_all_stages": true
      },
      "stages": [
        {
          "effect_type": "buff",
          "target": "allies",
          "kwargs": {
            "effect_no": 5,
            "buff_type": "dot_dmg_buff",
            "value_list": [0.1201, 0.1293, 0.1386, 0.1478, 0.157, 0.1663, 0.1755, 0.1848, 0.194, 0.2032],
            "duration": 10
          }
        },
        {
          "effect_type": "debuff",
          "target": "enemy",
          "kwargs": {
            "effect_no": 6,
            "buff_type": "taken_dmg_debuff",
            "value_list": [0.1904, 0.2051, 0.2197, 0.2344, 0.249, 0.2637, 0.2783, 0.293, 0.3076, 0.3223],
            "duration": 10,
            "description": "受けるダメージUP (dummy)"
          }
        }
      ]
    }
  ]
}